.gitignore
.travis.yml
CHANGES.txt
CONTRIBUTORS.txt
MANIFEST.in
README.rst
bootstrap.py
buildout.cfg
setup.py
travis.cfg
docs/LICENSE.GPL
docs/LICENSE.txt
src/theming/__init__.py
src/theming.toolkit.views.egg-info/PKG-INFO
src/theming.toolkit.views.egg-info/SOURCES.txt
src/theming.toolkit.views.egg-info/dependency_links.txt
src/theming.toolkit.views.egg-info/entry_points.txt
src/theming.toolkit.views.egg-info/namespace_packages.txt
src/theming.toolkit.views.egg-info/not-zip-safe
src/theming.toolkit.views.egg-info/requires.txt
src/theming.toolkit.views.egg-info/top_level.txt
src/theming/toolkit/__init__.py
src/theming/toolkit/views/__init__.py
src/theming/toolkit/views/configure.zcml
src/theming/toolkit/views/testing.py
src/theming/toolkit/views/testing.zcml
src/theming/toolkit/views/browser/__init__.py
src/theming/toolkit/views/browser/collectiontile.py
src/theming/toolkit/views/browser/configure.zcml
src/theming/toolkit/views/browser/interfaces.py
src/theming/toolkit/views/browser/tiles.zcml
src/theming/toolkit/views/browser/views.py
src/theming/toolkit/views/browser/templates/carousel-image-view.pt
src/theming/toolkit/views/browser/templates/carousel-portlet-view.pt
src/theming/toolkit/views/browser/templates/carousel-view-standard.pt
src/theming/toolkit/views/browser/templates/listing-carousel-view.pt
src/theming/toolkit/views/browser/templates/tiles_collection.pt
src/theming/toolkit/views/profiles/default/browserlayer.xml
src/theming/toolkit/views/profiles/default/metadata.xml
src/theming/toolkit/views/profiles/testing/metadata.xml
src/theming/toolkit/views/tests/__init__.py
src/theming/toolkit/views/tests/test_setup.py