Metadata-Version: 1.0
Name: theming.toolkit.views
Version: 0.3
Summary: Custom views for Plone Add-Ons.
Home-page: https://github.com/propertyshelf/theming.toolkit.views
Author: Propertyshelf, Inc.
Author-email: development@propertyshelf.com
License: gpl
Keywords: Plone Views Propertyshelf
Platform: UNKNOWN
Classifier: Environment :: Web Environment
Classifier: Operating System :: OS Independent
Classifier: Framework :: Zope2
Classifier: Framework :: Plone
Classifier: Framework :: Plone :: 4.2
Classifier: Framework :: Plone :: 4.3
Classifier: Programming Language :: Python
Classifier: Programming Language :: Python :: 2.6
Classifier: Programming Language :: Python :: 2.7
Classifier: Topic :: Software Development :: Libraries :: Python Modules
